{"cameraMode":{"drawMode":0,"name":"Shaded","section":"Shading Mode"},"sceneLighting":true,"audioPlay":false,"sceneViewState":{"showFog":true,"showMaterialUpdate":false,"showSkybox":true,"showFlares":true,"showImageEffects":true,"showParticleSystems":true},"in2DMode":false,"pivot":{"x":-4.076385498046875,"y":-6.949682235717773,"z":-3.99289608001709},"rotation":{"x":-0.029284384101629258,"y":0.9672791957855225,"z":-0.2155919075012207,"w":-0.1310642808675766},"size":37.85087585449219,"orthographic":false}